yomi/__init__.py
yomi/base.py
yomi/agents/__init__.py
yomi/agents/human_agent.py
yomi/agents/random_agent.py
yomi/agents/silly_tic_tac_toe.py
yomi/games/__init__.py
yomi/games/tictactoe.py
yomi/test/__init__.py
yomi/test/test_base.py
yomi-0.0.1.dist-info/METADATA
yomi-0.0.1.dist-info/WHEEL
yomi-0.0.1.dist-info/top_level.txt
yomi-0.0.1.dist-info/RECORD
