Metadata-Version: 2.1
Name: yomi
Version: 0.0.1
Summary: Tools for running tournaments of AI agents against each-other
Home-page: https://github.com/bluecoconut/yomi
License: UNKNOWN
Platform: UNKNOWN
Requires-Dist: numpy
Requires-Dist: pandas
Provides-Extra: dev
Requires-Dist: pytest ; extra == 'dev'
Requires-Dist: flake8 ; extra == 'dev'
